pypath_common/__init__.py
pypath_common/_constants.py
pypath_common/_logger.py
pypath_common/_misc.py
pypath_common/_session.py
pypath_common/_settings.py
pypath_common/data/__init__.py
pypath_common/data/_data.py
pypath_common/data/aacodes.yaml
pypath_common/data/aanames.yaml
pypath_common/data/amino_acids.yaml
pypath_common/data/idtypes/array.yaml
pypath_common/data/idtypes/biomart.yaml
pypath_common/data/idtypes/hmdb.yaml
pypath_common/data/idtypes/pro.yaml
pypath_common/data/idtypes/ramp.yaml
pypath_common/data/idtypes/uniprot.yaml
pypath_common/data/idtypes/uniprot_idmapping.yaml
pypath_common/data/igraph_graphics_attrs.yaml
pypath_common/data/mod_keywords.yaml
pypath_common/data/pmod_bel.yaml
pypath_common/data/psite_mod_types.yaml
pypath_common/data/psite_mod_types2.yaml
pypath_common/data/settings.yaml
pypath_common-0.2.6.dist-info/LICENSE
pypath_common-0.2.6.dist-info/METADATA
pypath_common-0.2.6.dist-info/WHEEL
pypath_common-0.2.6.dist-info/RECORD
